{
  "gameId": "sp4_card",
  "description": "Test sp-4 card nerf \u81ea\u7531/\u7d93\u6fdf traits both sides",
  "testType": "per_card",
  "initialGameEnv": {
    "phase": "BATTLE_PHASE",
    "round": 1,
    "gameStarted": true,
    "currentPlayer": "playerId_1",
    "currentTurn": 0,
    "firstPlayer": 0,
    "players": {
      "playerId_1": {
        "id": "playerId_1",
        "name": "Player 1",
        "deck": {
          "hand": [
            "sp-4",
            "c-1",
            "c-2",
            "c-3",
            "c-4"
          ],
          "mainDeck": [
            "c-5",
            "c-6",
            "c-7",
            "c-8",
            "c-9",
            "c-10",
            "c-11",
            "c-12",
            "c-13",
            "c-14",
            "c-15",
            "c-16",
            "h-2",
            "h-3",
            "h-4",
            "sp-1",
            "sp-2",
            "sp-3"
          ],
          "leader": [
            "s-1",
            "s-2",
            "s-3",
            "s-4"
          ],
          "currentLeaderIdx": 0
        },
        "isReady": true,
        "redraw": 1,
        "turnAction": [],
        "playerPoint": 0
      },
      "playerId_2": {
        "id": "playerId_2",
        "name": "Player 2",
        "deck": {
          "hand": [
            "c-17",
            "c-18",
            "c-19",
            "c-20",
            "c-21"
          ],
          "mainDeck": [
            "c-22",
            "c-23",
            "c-24",
            "c-25",
            "c-26",
            "c-27",
            "c-28",
            "c-29",
            "c-30",
            "c-31",
            "c-32",
            "c-33",
            "h-5",
            "h-6",
            "h-7",
            "sp-4",
            "sp-5",
            "sp-6"
          ],
          "leader": [
            "s-6",
            "s-2",
            "s-3",
            "s-4"
          ],
          "currentLeaderIdx": 0
        },
        "isReady": true,
        "redraw": 1,
        "turnAction": [],
        "playerPoint": 0
      }
    },
    "zones": {
      "playerId_1": {
        "leader": {
          "id": "s-1",
          "name": "\u7279\u6717\u666e",
          "cardType": "leader"
        },
        "top": [
          {
            "id": "c-freedom1",
            "name": "Freedom Character 1",
            "cardType": "character",
            "gameType": "\u81ea\u7531",
            "basePower": 75
          }
        ],
        "left": [],
        "right": [],
        "help": [],
        "sp": [
          {
            "id": "sp-4",
            "name": "\u95dc\u7a05\u6383\u5c04",
            "cardType": "sp",
            "effects": {
              "description": "\u5834\u4e0a\u5168\u90e8\u64c1\u6709\u81ea\u7531\u6216\u7d93\u6fdf\u7279\u5fb5\u89d2\u8272\u5361\uff0c\u539f\u80fd\u529b\u503c -50",
              "rules": [
                {
                  "id": "tariff_sweep_nerf",
                  "type": "continuous",
                  "target": {
                    "owner": "both",
                    "zones": [
                      "top",
                      "left",
                      "right"
                    ],
                    "filters": [
                      {
                        "type": "gameTypeOr",
                        "values": [
                          "\u81ea\u7531",
                          "\u7d93\u6fdf"
                        ]
                      }
                    ]
                  },
                  "effect": {
                    "type": "powerBoost",
                    "value": -50
                  }
                }
              ]
            }
          }
        ]
      },
      "playerId_2": {
        "leader": {
          "id": "s-2",
          "name": "\u62dc\u767b",
          "cardType": "leader"
        },
        "top": [
          {
            "id": "c-economy1",
            "name": "Economy Character 1",
            "cardType": "character",
            "gameType": "\u7d93\u6fdf",
            "basePower": 90
          }
        ],
        "left": [],
        "right": [],
        "help": [],
        "sp": []
      }
    },
    "gameEvents": [],
    "lastEventId": 1,
    "pendingPlayerAction": null,
    "pendingCardSelections": {},
    "playSequence": {
      "globalSequence": 0,
      "plays": []
    }
  },
  "playerActions": [],
  "validationPoints": {
    "sp4_both_sides_nerf": {
      "description": "sp-4 reduces \u81ea\u7531/\u7d93\u6fdf character power by -50 on both sides",
      "expected": {
        "allyFreedomPowerBefore": 75,
        "allyFreedomPowerAfter": 25,
        "opponentEconomyPowerBefore": 90,
        "opponentEconomyPowerAfter": 40,
        "bothSidesAffected": true,
        "nerfValue": -50
      }
    }
  }
}